zapformer/__init__.py
zapformer-0.1.0.dist-info/METADATA
zapformer-0.1.0.dist-info/WHEEL
zapformer-0.1.0.dist-info/top_level.txt
zapformer-0.1.0.dist-info/RECORD
